./LICENSE
./PKG-INFO
./README.md
./build.sh
./publish.sh
./pyproject.toml
./whatsnew.txt
./.idea/.gitignore
./.idea/a2a-acl.iml
./.idea/misc.xml
./.idea/modules.xml
./.idea/vcs.xml
./.idea/workspace.xml
./.idea/inspectionProfiles/Project_Default.xml
./.idea/inspectionProfiles/profiles_settings.xml
./.idea/shelf/Uncommitted_changes_before_Checkout_at_16_01_2026_11_23__Changes_.xml
./.idea/shelf/Uncommitted_changes_before_Merge_at_16_01_2026_11_23__Changes_.xml
./.idea/shelf/Uncommitted_changes_before_Checkout_at_16_01_2026_11_23_[Changes]/shelved.patch
./.idea/shelf/Uncommitted_changes_before_Merge_at_16_01_2026_11_23_[Changes]/shelved.patch
./a2a_acl/__init__.py
./a2a_acl/a2a_utils/__init__.py
./a2a_acl/a2a_utils/card_holder.py
./a2a_acl/a2a_utils/send_message.py
./a2a_acl/agent/__init__.py
./a2a_acl/agent/acl_agent.py
./a2a_acl/agent/server_utils.py
./a2a_acl/content_codecs/__init__.py
./a2a_acl/content_codecs/atom_codec.py
./a2a_acl/content_codecs/common.py
./a2a_acl/content_codecs/python_codec.py
./a2a_acl/interface/__init__.py
./a2a_acl/interface/asi_parser.py
./a2a_acl/interface/card_conversion.py
./a2a_acl/interface/interface.py
./a2a_acl/interface/skill_conversion.py
./a2a_acl/protocol/MOSAICO_A2A_ACL_PROTOCOL
./a2a_acl/protocol/__init__.py
./a2a_acl/protocol/acl_message.py
./a2a_acl/protocol/message_codec.py
./a2a_acl/protocol/send_acl_message.py
./a2a_acl/translator_nl_to_acl/__init__.py
./a2a_acl/translator_nl_to_acl/mistral_config.py
./a2a_acl/translator_nl_to_acl/translator.py
./a2a_acl/utils/__init__.py
./a2a_acl/utils/result.py
./a2a_acl/utils/strings.py
./a2a_acl/utils/url.py
./sample_agents/human_validation/context.py
./sample_agents/human_validation/human_validator.asi
./sample_agents/human_validation/human_validator.py
./sample_agents/human_validation/run_validator_agent.py
./sample_agents/llm_refactoring_advice/advisor.asi
./sample_agents/llm_refactoring_advice/advisor.py
./sample_agents/llm_refactoring_advice/context.py
a2a_acl-0.0.12.dist-info/METADATA
a2a_acl-0.0.12.dist-info/WHEEL
a2a_acl-0.0.12.dist-info/licenses/LICENSE
a2a_acl-0.0.12.dist-info/RECORD
