Metadata-Version: 2.4
Name: a2a-acl
Version: 0.0.12
Summary: ACL agents on A2A protocol.
Project-URL: Homepage, https://gitlab.eclipse.org/eclipse-research-labs/mosaico-project/a2a-acl
Author-email: Julien Cohen <Julien.Cohen@imt-atlantique.fr>, Massimo Tisi <Massimo.Tisi@imt-atlantique.fr>
Maintainer-email: Julien Cohen <Julien.Cohen@imt-atlantique.fr>, Massimo Tisi <Massimo.Tisi@imt-atlantique.fr>
License-Expression: EPL-2.0
License-File: LICENSE
Keywords: A2A,ACL
Classifier: Development Status :: 3 - Alpha
Classifier: Intended Audience :: Developers
Requires-Python: >=3.12
Requires-Dist: a2a-sdk[http-server]==0.3.22
Requires-Dist: uvicorn[standard]>=0.38.0
